metpysdk/__init__.py
metpysdk/accounts/__init__.py
metpysdk/accounts/bins.py
metpysdk/accounts/clock.py
metpysdk/accounts/fee.py
metpysdk/accounts/get_positions.py
metpysdk/accounts/lb_pair.py
metpysdk/accounts/position.py
metpysdk/accounts/primitives.py
metpysdk/accounts/token.py
metpysdk/constants/__init__.py
metpysdk/constants/limits.py
metpysdk/constants/math.py
metpysdk/constants/program.py
metpysdk/dlmm/__init__.py
metpysdk/dlmm/client.py
metpysdk/dlmm/dlmm_core.py
metpysdk/helpers/__init__.py
metpysdk/helpers/bins.py
metpysdk/helpers/positions.py
metpysdk/instructions/__init__.py
metpysdk/instructions/add_liquidity.py
metpysdk/instructions/claim_fees.py
metpysdk/instructions/close_position.py
metpysdk/instructions/initialize_position.py
metpysdk/instructions/remove_liquidity.py
metpysdk/layouts/__init__.py
metpysdk/layouts/bin.py
metpysdk/layouts/clock.py
metpysdk/layouts/discriminators.py
metpysdk/layouts/lb_pair.py
metpysdk/layouts/parameters.py
metpysdk/layouts/position.py
metpysdk/layouts/primitives.py
metpysdk/layouts/rewards.py
metpysdk/maths/__init__.py
metpysdk/maths/bins.py
metpysdk/maths/liquidity.py
metpysdk/maths/price.py
metpysdk/maths/rewards.py
metpysdk/utils/__init__.py
metpysdk/utils/bitmap.py
metpysdk/utils/constants.py
metpysdk/utils/derivation.py
metpysdk/utils/filters.py
metpysdk/utils/rpc.py
metpysdk-0.2.1.dist-info/licenses/LICENSE
metpysdk-0.2.1.dist-info/METADATA
metpysdk-0.2.1.dist-info/WHEEL
metpysdk-0.2.1.dist-info/RECORD
