Metadata-Version: 2.4
Name: metpysdk
Version: 0.2.1
Summary: METEORA DLMM SDK
License: MIT
License-File: LICENSE
Author: Ivan Bezborodov
Requires-Python: >=3.9,<4.0
Classifier: License :: OSI Approved :: MIT License
Classifier: Programming Language :: Python :: 3
Classifier: Programming Language :: Python :: 3.9
Classifier: Programming Language :: Python :: 3.10
Classifier: Programming Language :: Python :: 3.11
Classifier: Programming Language :: Python :: 3.12
Classifier: Programming Language :: Python :: 3.13
Classifier: Programming Language :: Python :: 3.14
Provides-Extra: dev
Requires-Dist: base58 (>=2.1.1,<3.0.0)
Requires-Dist: construct (>=2.10,<3.0)
Requires-Dist: mypy (>=1.8,<2.0) ; extra == "dev"
Requires-Dist: pylint (>=3.0,<4.0) ; extra == "dev"
Requires-Dist: pytest (>=8.0,<9.0) ; extra == "dev"
Requires-Dist: ruff (>=0.6,<1.0) ; extra == "dev"
Requires-Dist: solana (>=0.36.10,<0.37.0)
Requires-Dist: solders (>=0.27.1,<0.28.0)
